budgetcli/__init__.py
budgetcli/auth.py
budgetcli/commands.py
budgetcli/data_manager.py
budgetcli/main.py
budgetcli/models.py
budgetcli/settings.py
budgetcli/cli/__init__.py
budgetcli/cli/add.py
budgetcli/cli/config.py
budgetcli/cli/display.py
budgetcli/utils/__init__.py
budgetcli/utils/config.py
budgetcli/utils/dates.py
budgetcli/utils/display.py
budgetcli-2.0.0.dist-info/LICENSE
budgetcli-2.0.0.dist-info/METADATA
budgetcli-2.0.0.dist-info/WHEEL
budgetcli-2.0.0.dist-info/entry_points.txt
budgetcli-2.0.0.dist-info/top_level.txt
budgetcli-2.0.0.dist-info/RECORD
