Metadata-Version: 2.1
Name: budgetcli
Version: 2.0.0
Summary: A simple async budgeting app to manage expenses and budgets in google spreadsheets
Author: Code Rustle
Author-email: coderustle@gmail.com
License: MIT
Classifier: Topic :: Utilities
Classifier: Intended Audience :: End Users/Desktop
Classifier: License :: OSI Approved :: MIT License
Classifier: Operating System :: OS Independent
Classifier: Programming Language :: Python :: 3.11
License-File: LICENSE
Requires-Dist: typer[all]
Requires-Dist: google-auth
Requires-Dist: google-auth-httplib2
Requires-Dist: google-api-python-client
Requires-Dist: google-auth-oauthlib
Requires-Dist: platformdirs
Requires-Dist: httpx
